browser_cookie_3x/__init__.py
browser_cookie_3x-0.19.1.dist-info/LICENSE
browser_cookie_3x-0.19.1.dist-info/METADATA
browser_cookie_3x-0.19.1.dist-info/WHEEL
browser_cookie_3x-0.19.1.dist-info/top_level.txt
browser_cookie_3x-0.19.1.dist-info/RECORD
